setup.cfg
setup.py
Akimka_001/__int__.py
Akimka_001/взаимодействие_с_ТГ.py
Akimka_001/проверка_элемента.py
Akimka_001/работа_с_файлами.py
Akimka_001/терминал.py
Akimka_001/тест.py
Akimka_001/тесты теория.py
Akimka_tools.egg-info/PKG-INFO
Akimka_tools.egg-info/SOURCES.txt
Akimka_tools.egg-info/dependency_links.txt
Akimka_tools.egg-info/not-zip-safe
Akimka_tools.egg-info/top_level.txt