Metadata-Version: 2.1
Name: Akimka-tools
Version: 0.5
Summary: Мои инструменты
Author-email: akimov.konstantin.2024@gmail.com
